mkdocs_literate_nav/__init__.py
mkdocs_literate_nav/exceptions.py
mkdocs_literate_nav/parser.py
mkdocs_literate_nav/plugin.py
mkdocs_literate_nav/py.typed
mkdocs_literate_nav-0.6.0.dist-info/METADATA
mkdocs_literate_nav-0.6.0.dist-info/WHEEL
mkdocs_literate_nav-0.6.0.dist-info/entry_points.txt
mkdocs_literate_nav-0.6.0.dist-info/licenses/LICENSE.md
mkdocs_literate_nav-0.6.0.dist-info/RECORD
