Metadata-Version: 2.1
Name: mkdocs-literate-nav
Version: 0.6.0
Summary: MkDocs plugin to specify the navigation in Markdown instead of YAML
Project-URL: Documentation, https://oprypin.github.io/mkdocs-literate-nav/
Project-URL: Source, https://github.com/oprypin/mkdocs-literate-nav
Project-URL: Issues, https://github.com/oprypin/mkdocs-literate-nav/issues
Project-URL: History, https://github.com/oprypin/mkdocs-literate-nav/releases
Author-email: Oleh Prypin <oleh@pryp.in>
License-Expression: MIT
License-File: LICENSE.md
Keywords: mkdocs,mkdocs-plugin
Classifier: Development Status :: 4 - Beta
Classifier: Environment :: Console
Classifier: Environment :: Web Environment
Classifier: Intended Audience :: Information Technology
Classifier: License :: OSI Approved :: MIT License
Classifier: Operating System :: OS Independent
Classifier: Programming Language :: Python
Classifier: Programming Language :: Python :: 3.7
Classifier: Programming Language :: Python :: 3.8
Classifier: Programming Language :: Python :: 3.9
Classifier: Programming Language :: Python :: 3.10
Classifier: Programming Language :: Python :: 3.11
Classifier: Topic :: Documentation
Classifier: Topic :: Software Development :: Documentation
Classifier: Topic :: Text Processing :: Markup :: Markdown
Classifier: Typing :: Typed
Requires-Python: >=3.7
Requires-Dist: mkdocs>=1.0.3
